docme/__init__.py
docme/cli.py
docme/builders/__init__.py
docme/builders/components.py
docme/builders/structures.py
docme/builders/utils.py
docme/builders/writer.py
docme/builders/components/__init__.py
docme/builders/components/base_component.py
docme/builders/components/function.py
docme/builders/components/klass.py
docme/builders/components/module.py
docme/builders/components/toctree.py
docme/builders/components/utils.py
docme/components/__init__.py
docme/components/base_component.py
docme/components/function.py
docme/components/klass.py
docme/components/module.py
docme/components/toctree.py
docme/components/utils.py
docme-0.5.0.dist-info/LICENSE
docme-0.5.0.dist-info/METADATA
docme-0.5.0.dist-info/WHEEL
docme-0.5.0.dist-info/entry_points.txt
docme-0.5.0.dist-info/top_level.txt
docme-0.5.0.dist-info/RECORD
