Metadata-Version: 2.1
Name: docme
Version: 0.5.0
Summary: Auto documentation generating
Home-page: UNKNOWN
Author: Elran Shefer
Author-email: elran777@gmail.com
License: MIT
Keywords: doc
Platform: UNKNOWN
Classifier: License :: OSI Approved :: MIT License
Classifier: Topic :: Software Development :: Testing
Classifier: Intended Audience :: Developers
Classifier: Programming Language :: Python :: 2
Classifier: Programming Language :: Python :: 2.7
Classifier: Programming Language :: Python :: 3
Classifier: Programming Language :: Python :: 3.5
Classifier: Programming Language :: Python :: 3.6
Classifier: Programming Language :: Python :: 3.7
Classifier: Operating System :: Microsoft :: Windows
Classifier: Operating System :: POSIX
Classifier: Operating System :: Unix
Classifier: Operating System :: MacOS
Requires-Python: >=2.7,!=3.0.*,!=3.1.*,!=3.2.*,!=3.3.*,!=3.4.*
Requires-Dist: pyyaml
